{"id":"grained","name":"grained.js — Film Grain Noise Overlay","category":"texture","license":"MIT","repo":"https://github.com/sarathsaleem/grained","description":"Adds an animated CSS film grain/noise texture over any element for a premium cinematic feel. Great on hero sections and dark backgrounds.","head":"<style>\n  [data-grained] { position: relative; isolation: isolate; }\n</style>","body":"<script src=\"https://cdn.jsdelivr.net/npm/grained@0.0.2/grained.js\"></script>\n<script>\n  document.addEventListener('DOMContentLoaded', function () {\n    document.querySelectorAll('[data-grained]').forEach(function (el) {\n      if (!el.id) el.id = 'grained-' + Math.random().toString(36).slice(2);\n      grained('#' + el.id, { animate: true, patternWidth: 100, patternHeight: 100,\n        grainOpacity: parseFloat(el.getAttribute('data-grained-opacity') || '0.04'),\n        grainDensity: 1, grainWidth: 1, grainHeight: 1, speed: 0.8 });\n    });\n  });\n</script>"}
